mongodb_connector/__init__.py
mongodb_connector/connector/__init__.py
mongodb_connector/connector/mongo.py
mongodb_connector/models/__init__.py
mongodb_connector/models/data_models.py
goldberg_mongodb_connector-0.1.0.dist-info/LICENSE
goldberg_mongodb_connector-0.1.0.dist-info/WHEEL
goldberg_mongodb_connector-0.1.0.dist-info/METADATA
goldberg_mongodb_connector-0.1.0.dist-info/RECORD
